interpretable_tsne-0.0.4.dist-info/RECORD
interpretable_tsne-0.0.4.dist-info/top_level.txt
interpretable_tsne-0.0.4.dist-info/WHEEL
interpretable_tsne-0.0.4.dist-info/METADATA
interpretable_tsne-0.0.4.dist-info/COPYING
interpretable_tsne/umap.py
interpretable_tsne/tsne.py
interpretable_tsne/_utils.pyx
interpretable_tsne/_utils.pxd
interpretable_tsne/_utils.cpython-310-x86_64-linux-gnu.so
interpretable_tsne/_utils.c
interpretable_tsne/_quad_tree.pyx
interpretable_tsne/_quad_tree.pxd
interpretable_tsne/_quad_tree.cpython-310-x86_64-linux-gnu.so
interpretable_tsne/_quad_tree.c
interpretable_tsne/_grad_comps.pyx
interpretable_tsne/_grad_comps.cpython-310-x86_64-linux-gnu.so
interpretable_tsne/_grad_comps.c
interpretable_tsne/_bintree.pyx
interpretable_tsne/_bintree.cpython-310-x86_64-linux-gnu.so
interpretable_tsne/_bintree.c
interpretable_tsne/_barnes_hut_tsne.pyx
interpretable_tsne/_barnes_hut_tsne.cpython-310-x86_64-linux-gnu.so
interpretable_tsne/_barnes_hut_tsne.c
interpretable_tsne/__init__.py
