Metadata-Version: 2.1
Name: interpretable_tsne
Version: 0.0.4
Summary: Implementation of the gradient-based t-SNE attribution method described in our GLBIO oral presentation: 'Towards Computing Attributions for Dimensionality Reduction Techniques'
Author: Matthew Scicluna
Author-email: Matthew Scicluna <mattcscicluna@gmail.com>
Maintainer-email: Matthew Scicluna <mattcscicluna@gmail.com>
License: BSD 3-Clause License
Project-URL: Repository, https://github.com/MattScicluna/interpretable_tsne.git
Project-URL: Bug Tracker, https://github.com/MattScicluna/interpretable_tsne/issues
Classifier: Programming Language :: Python :: 3
Classifier: License :: OSI Approved :: BSD License
Classifier: Operating System :: OS Independent
Requires-Python: >=3.7
License-File: COPYING
Requires-Dist: scikit-learn >=0.23.0
Requires-Dist: scipy >=1.5.0
Requires-Dist: numpy >=1.19.2
